openapi_31/__init__.py
openapi_31/py.typed
openapi_31-0.2.0.dist-info/METADATA
openapi_31-0.2.0.dist-info/WHEEL
openapi_31-0.2.0.dist-info/top_level.txt
openapi_31-0.2.0.dist-info/RECORD
