Metadata-Version: 2.1
Name: openapi-31
Version: 0.2.0
Summary: OpenAPI 3.1 models for Python! 🐍
Requires-Python: >=3.8
Requires-Dist: pydantic>=2.9
